frequenz/client/electricity_trading/__init__.py
frequenz/client/electricity_trading/_client.py
frequenz/client/electricity_trading/_types.py
frequenz/client/electricity_trading/_utils.py
frequenz/client/electricity_trading/conftest.py
frequenz/client/electricity_trading/py.typed
frequenz/client/electricity_trading/cli/__init__.py
frequenz/client/electricity_trading/cli/__main__.py
frequenz/client/electricity_trading/cli/day_ahead.py
frequenz/client/electricity_trading/cli/etrading.py
frequenz_client_electricity_trading-0.15.0.dist-info/licenses/LICENSE
frequenz_client_electricity_trading-0.15.0.dist-info/METADATA
frequenz_client_electricity_trading-0.15.0.dist-info/WHEEL
frequenz_client_electricity_trading-0.15.0.dist-info/entry_points.txt
frequenz_client_electricity_trading-0.15.0.dist-info/top_level.txt
frequenz_client_electricity_trading-0.15.0.dist-info/RECORD
